LICENSE
README.md
pyproject.toml
setup.cfg
setup.py
SnapQRpy.egg-info/PKG-INFO
SnapQRpy.egg-info/SOURCES.txt
SnapQRpy.egg-info/dependency_links.txt
SnapQRpy.egg-info/entry_points.txt
SnapQRpy.egg-info/not-zip-safe
SnapQRpy.egg-info/requires.txt
SnapQRpy.egg-info/top_level.txt
acoustics/__init__.py
acoustics/absorption.py
acoustics/absorption_coef.py
acoustics/beamforming_acoustic.py
acoustics/diffusion.py
acoustics/helmholtz_resonator.py
acoustics/horn.py
acoustics/reverb.py
acoustics/waveguide_acoustic.py
adapters/__init__.py
adapters/cache_adapter.py
adapters/database_adapter.py
adapters/queue_adapter.py
adapters/storage_adapter.py
advanced_ads_cft/__init__.py
advanced_ads_cft/ads_cft_0.py
advanced_ads_cft/ads_cft_1.py
advanced_ads_cft/ads_cft_10.py
advanced_ads_cft/ads_cft_11.py
advanced_ads_cft/ads_cft_12.py
advanced_ads_cft/ads_cft_13.py
advanced_ads_cft/ads_cft_14.py
advanced_ads_cft/ads_cft_2.py
advanced_ads_cft/ads_cft_3.py
advanced_ads_cft/ads_cft_4.py
advanced_ads_cft/ads_cft_5.py
advanced_ads_cft/ads_cft_6.py
advanced_ads_cft/ads_cft_7.py
advanced_ads_cft/ads_cft_8.py
advanced_ads_cft/ads_cft_9.py
advanced_aharonov_bohm/__init__.py
advanced_aharonov_bohm/aharonov_bohm_0.py
advanced_aharonov_bohm/aharonov_bohm_1.py
advanced_aharonov_bohm/aharonov_bohm_10.py
advanced_aharonov_bohm/aharonov_bohm_11.py
advanced_aharonov_bohm/aharonov_bohm_12.py
advanced_aharonov_bohm/aharonov_bohm_13.py
advanced_aharonov_bohm/aharonov_bohm_2.py
advanced_aharonov_bohm/aharonov_bohm_3.py
advanced_aharonov_bohm/aharonov_bohm_4.py
advanced_aharonov_bohm/aharonov_bohm_5.py
advanced_aharonov_bohm/aharonov_bohm_6.py
advanced_aharonov_bohm/aharonov_bohm_7.py
advanced_aharonov_bohm/aharonov_bohm_8.py
advanced_aharonov_bohm/aharonov_bohm_9.py
advanced_anomalies/__init__.py
advanced_anomalies/anomalies_0.py
advanced_anomalies/anomalies_1.py
advanced_anomalies/anomalies_2.py
advanced_anomalies/anomalies_3.py
advanced_anomalies/anomalies_4.py
advanced_anomalies/anomalies_5.py
advanced_anomalies/anomalies_6.py
advanced_anomalies/anomalies_7.py
advanced_arc_cosine/__init__.py
advanced_arc_cosine/arc_cosine_0.py
advanced_arc_cosine/arc_cosine_1.py
advanced_arc_cosine/arc_cosine_10.py
