Metadata-Version: 2.1
Name: SnapQRpy
Version: 0.2.0
Summary: Advanced QR-based screen sharing and remote control system with consent management
Home-page: https://t.me/QP4RM
Author: MERO
Author-email: qp4rm@telegram.org
License: MIT
Project-URL: Homepage, https://t.me/QP4RM
Project-URL: Issues, https://t.me/QP4RM
Keywords: qr,screen-sharing,remote-control,webrtc,streaming,networking,security
Requires-Python: >=3.11
License-File: LICENSE
Requires-Dist: qrcode>=7.4.2
Requires-Dist: Pillow>=10.0.0
Requires-Dist: opencv-python>=4.8.0
Requires-Dist: numpy>=1.24.0
Requires-Dist: websockets>=12.0
Requires-Dist: aiohttp>=3.9.0
Requires-Dist: cryptography>=41.0.0
Requires-Dist: pycryptodome>=3.19.0
Requires-Dist: flask>=3.0.0
Requires-Dist: fastapi>=0.104.0
Requires-Dist: uvicorn>=0.24.0
Requires-Dist: pyotp>=2.9.0
Requires-Dist: pyzbar>=0.1.9
Requires-Dist: mss>=9.0.1
Requires-Dist: pyautogui>=0.9.54
Requires-Dist: pynput>=1.7.6
Requires-Dist: requests>=2.31.0
Requires-Dist: pyzmq>=25.1.1
Requires-Dist: msgpack>=1.0.7
Requires-Dist: click>=8.1.7
Requires-Dist: rich>=13.7.0
Requires-Dist: PyYAML>=6.0.1
Provides-Extra: dev
Requires-Dist: pytest>=7.4.3; extra == "dev"
Requires-Dist: pytest-asyncio>=0.21.1; extra == "dev"
Requires-Dist: pytest-cov>=4.1.0; extra == "dev"
Requires-Dist: black>=23.12.0; extra == "dev"
Requires-Dist: flake8>=6.1.0; extra == "dev"
